arushigupta11_101703106_missing/__init__.py
arushigupta11_101703106_missing/missingdata1.py
arushigupta_101703106_missing-0.0.1.dist-info/LICENSE
arushigupta_101703106_missing-0.0.1.dist-info/METADATA
arushigupta_101703106_missing-0.0.1.dist-info/WHEEL
arushigupta_101703106_missing-0.0.1.dist-info/top_level.txt
arushigupta_101703106_missing-0.0.1.dist-info/RECORD
