Metadata-Version: 2.1
Name: arushigupta-101703106-missing
Version: 0.0.1
Summary: A small package that handles missing values in pandas dataframe
Home-page: UNKNOWN
Author: Arushi Gupta
Author-email: agupta11_be17@thapar.edu
License: UNKNOWN
Platform: UNKNOWN
Classifier: Programming Language :: Python :: 3
Classifier: License :: OSI Approved :: MIT License
Classifier: Operating System :: OS Independent
Requires-Python: >=3.6
